openfisca_france_reforms/__init__.py
openfisca_france_reforms/landais_piketty_saez/__init__.py
openfisca_france_reforms/landais_piketty_saez/parameters.yaml
openfisca_france_reforms/lfi_progressivite_bareme_impot_revenu/__init__.py
openfisca_france_reforms/lfi_progressivite_bareme_impot_revenu/parameters.yaml
openfisca_france_reforms/plf_2022/__init__.py
openfisca_france_reforms/plf_2022/aah.py
openfisca_france_reforms/plf_2022/parameters/impot_revenu/abattements_rni/enfant_marie/montant.yaml
openfisca_france_reforms/plf_2022/parameters/impot_revenu/bareme.yaml
openfisca_france_reforms/plf_2022/parameters/impot_revenu/decote/seuil_celib.yaml
openfisca_france_reforms/plf_2022/parameters/impot_revenu/decote/seuil_couple.yaml
openfisca_france_reforms/plf_2022/parameters/impot_revenu/plafond_qf/celib.yaml
openfisca_france_reforms/plf_2022/parameters/impot_revenu/plafond_qf/celib_enf.yaml
openfisca_france_reforms/plf_2022/parameters/impot_revenu/plafond_qf/general.yaml
openfisca_france_reforms/plf_2022/parameters/impot_revenu/plafond_qf/reduc_postplafond.yaml
openfisca_france_reforms/plf_2022/parameters/impot_revenu/plafond_qf/reduc_postplafond_veuf.yaml
openfisca_france_reforms/plf_2022/parameters/prestations_sociales/prestations_etat_de_sante/invalidite/aah/abattement_conjoint.yaml
openfisca_france_reforms/plf_2022/parameters/prestations_sociales/prestations_etat_de_sante/invalidite/aah/abattement_conjoint_salarie_forfait.yaml
openfisca_france_reforms/plf_2022/parameters/prestations_sociales/prestations_etat_de_sante/invalidite/aah/abattement_conjoint_salarie_forfait_enfant.yaml
openfisca_france_reforms/plf_2022/scripts/__init__.py
openfisca_france_reforms/plf_2022/scripts/run_test.py
openfisca_france_reforms/plf_2022/tests_apres_reforme/aah.yaml
openfisca_france_reforms/plf_2022/tests_avant_reforme/aah.yaml
openfisca_france_reforms/reforme_test_1/__init__.py
openfisca_france_reforms/reforme_test_1/parameters/impot_revenu/bareme_ir_depuis_1945/bareme.yaml
openfisca_france_reforms-1.0.116.dist-info/entry_points.txt
openfisca_france_reforms-1.0.116.dist-info/LICENSE.md
openfisca_france_reforms-1.0.116.dist-info/WHEEL
openfisca_france_reforms-1.0.116.dist-info/METADATA
openfisca_france_reforms-1.0.116.dist-info/RECORD
