Metadata-Version: 2.1
Name: openfisca-france-reforms
Version: 1.0.116
Summary: Some reforms for French OpenFisca tax-benefit system
Home-page: https://git.leximpact.dev/leximpact/openfisca-france-reforms
License: http://www.fsf.org/licensing/licenses/agpl-3.0.html
Keywords: benefit,france,microsimulation,reform,social,tax
Author: Emmanuel Raviart
Author-email: emmanuel@raviart.com
Requires-Python: >=3.7
Classifier: License :: Other/Proprietary License
Classifier: Programming Language :: Python :: 3
Classifier: Programming Language :: Python :: 3.10
Classifier: Programming Language :: Python :: 3.7
Classifier: Programming Language :: Python :: 3.8
Classifier: Programming Language :: Python :: 3.9
Requires-Dist: openfisca-france (>=116.13.2)
Project-URL: Repository, https://git.leximpact.dev/leximpact/openfisca-france-reforms
